MudlogPy/Mudlog.py
MudlogPy/__init__.py
MudlogPy-0.1.0.dist-info/METADATA
MudlogPy-0.1.0.dist-info/WHEEL
MudlogPy-0.1.0.dist-info/top_level.txt
MudlogPy-0.1.0.dist-info/RECORD
