Metadata-Version: 2.1
Name: MudlogPy
Version: 0.1.0
Summary: This library plots the mudlog having gas chromatograph and lithology logs
Author: Landmark Resources Reservoir Characterization Department
